Products.orderedbtreefolder-3.2-py3.11-nspkg.pth
Products/orderedbtreefolder/LICENSE.GPL
Products/orderedbtreefolder/LICENSE.txt
Products/orderedbtreefolder/README.rst
Products/orderedbtreefolder/__init__.py
Products/orderedbtreefolder/orderedbtreefolder.gif
Products/orderedbtreefolder/orderedbtreefolder.py
Products/orderedbtreefolder/dtml/orderedBTFolderMain.dtml
Products/orderedbtreefolder/dtml/orderedFolderAdd.dtml
Products/orderedbtreefolder/tests/__init__.py
Products/orderedbtreefolder/tests/test_orderedbtreefolder.py
Products.orderedbtreefolder-3.2.dist-info/LICENSE.txt
Products.orderedbtreefolder-3.2.dist-info/METADATA
Products.orderedbtreefolder-3.2.dist-info/WHEEL
Products.orderedbtreefolder-3.2.dist-info/namespace_packages.txt
Products.orderedbtreefolder-3.2.dist-info/top_level.txt
Products.orderedbtreefolder-3.2.dist-info/RECORD
