Metadata-Version: 2.1
Name: Products.orderedbtreefolder
Version: 3.2
Summary: BTree folder with the option to keep an ordering in the items
Home-page: https://gitlab.com/gocept/union.cms/products.orderedbtreefolder
Author: union.cms developers
Author-email: dev@unioncms.org
License: GPL
Keywords: union.cms zope python content
Classifier: Framework :: Zope :: 4
Classifier: Framework :: Zope :: 5
Classifier: Programming Language :: Python :: 3
Classifier: Programming Language :: Python :: 3.7
Classifier: Programming Language :: Python :: 3.8
Classifier: Programming Language :: Python :: 3.9
Classifier: Programming Language :: Python :: 3.10
Classifier: Programming Language :: Python :: 3.11
Classifier: Programming Language :: Python :: Implementation :: CPython
Classifier: Topic :: Software Development :: Libraries :: Python Modules
Classifier: Intended Audience :: Developers
Classifier: License :: OSI Approved :: GNU General Public License (GPL)
Classifier: Development Status :: 5 - Production/Stable
Requires-Python: >=3.7, <4
License-File: LICENSE.txt
Requires-Dist: AccessControl
Requires-Dist: Acquisition
Requires-Dist: Products.BTreeFolder2 (>=4)
Requires-Dist: Products.ZCatalog
Requires-Dist: ZODB
Requires-Dist: Zope (>=4.0b7)
Requires-Dist: setuptools
Requires-Dist: zExceptions
Provides-Extra: test
Requires-Dist: zope.testing (>=3.8) ; extra == 'test'
